Metadata-Version: 1.0
Name: test-test-leon
Version: 0.1
Summary: 输入举行
Home-page: UNKNOWN
Author: leon.hu
Author-email: sdcxhuoxiaoqi@126.com
License: MIT
Platform: Linux
